plex_leon/__init__.py
plex_leon/api/__init__.py
plex_leon/api/tvdb_client.py
plex_leon/cli/__init__.py
plex_leon/cli/help.py
plex_leon/cli/menu.py
plex_leon/main.py
plex_leon/shared/__init__.py
plex_leon/shared/assert_required_tools_installed.py
plex_leon/shared/collect_tvdb_ids.py
plex_leon/shared/extract_tvdb_id.py
plex_leon/shared/file_size.py
plex_leon/shared/find_episode_in_dirs.py
plex_leon/shared/format_bytes.py
plex_leon/shared/format_resolution.py
plex_leon/shared/get_season_number_from_dirname.py
plex_leon/shared/is_season_like_dirname.py
plex_leon/shared/iter_nonhidden_entries.py
plex_leon/shared/merge_directory_contents.py
plex_leon/shared/move_file.py
plex_leon/shared/normalize_episode_tag.py
plex_leon/shared/parse_episode_tag.py
plex_leon/shared/parse_season_episode.py
plex_leon/shared/read_video_resolution.py
plex_leon/shared/remove_dir_if_empty.py
plex_leon/shared/strip_tvdb_suffix.py
plex_leon/shared/two_step_case_rename.py
plex_leon/shared/unique_swap_path.py
plex_leon/shared/utility_discovery.py
plex_leon/utils/__init__.py
plex_leon/utils/base_utility.py
plex_leon/utils/episode_check.py
plex_leon/utils/episode_renamer.py
plex_leon/utils/migrate.py
plex_leon/utils/prepare.py
plex_leon/utils/season_renamer.py
plex_leon-3.1.0.dist-info/METADATA
plex_leon-3.1.0.dist-info/WHEEL
plex_leon-3.1.0.dist-info/entry_points.txt
plex_leon-3.1.0.dist-info/licenses/LICENSE
plex_leon-3.1.0.dist-info/RECORD
