Metadata-Version: 2.4
Name: plex-leon
Version: 3.1.0
Summary: 
License-File: LICENSE
Author: Felix Rizzolli
Author-email: felix.rizzolli@outlook.de
Requires-Python: >=3.14,<4.0
Classifier: Programming Language :: Python :: 3
Classifier: Programming Language :: Python :: 3.14
Requires-Dist: coverage (>=7.13.0,<8.0.0)
Requires-Dist: loguru (>=0.7.3,<0.8.0)
Requires-Dist: pytest (>=9.0.2,<10.0.0)
Requires-Dist: requests (>=2.31.0,<3.0.0)
